<?xml version="1.0" encoding="UTF-8"?><record_update>
    <sys_choice action="DELETE" field="state" table="x_58872_needit_needit" version="3">
        <sys_choice action="INSERT_OR_UPDATE">
            <dependent_value/>
            <element>state</element>
            <hint/>
            <inactive>false</inactive>
            <label>Requested</label>
            <language>en</language>
            <name>x_58872_needit_needit</name>
            <sequence>0</sequence>
            <sys_created_by>admin</sys_created_by>
            <sys_created_on>2017-01-26 20:14:39</sys_created_on>
            <sys_domain>global</sys_domain>
            <sys_domain_path>/</sys_domain_path>
            <sys_id>e0b229350fa03200cd674f8ce1050ea9</sys_id>
            <sys_mod_count>0</sys_mod_count>
            <sys_updated_by>admin</sys_updated_by>
            <sys_updated_on>2017-01-26 20:14:39</sys_updated_on>
            <value>13</value>
        </sys_choice>
        <sys_choice action="INSERT_OR_UPDATE">
            <dependent_value/>
            <element>state</element>
            <hint/>
            <inactive>false</inactive>
            <label>Awaiting Approval</label>
            <language>en</language>
            <name>x_58872_needit_needit</name>
            <sequence>1</sequence>
            <sys_created_by>admin</sys_created_by>
            <sys_created_on>2017-01-26 20:14:39</sys_created_on>
            <sys_domain>global</sys_domain>
            <sys_domain_path>/</sys_domain_path>
            <sys_id>ecb229350fa03200cd674f8ce1050eaa</sys_id>
            <sys_mod_count>0</sys_mod_count>
            <sys_updated_by>admin</sys_updated_by>
            <sys_updated_on>2017-01-26 20:14:39</sys_updated_on>
            <value>14</value>
        </sys_choice>
        <sys_choice action="INSERT_OR_UPDATE">
            <dependent_value/>
            <element>state</element>
            <hint/>
            <inactive>false</inactive>
            <label>Approved</label>
            <language>en</language>
            <name>x_58872_needit_needit</name>
            <sequence>2</sequence>
            <sys_created_by>admin</sys_created_by>
            <sys_created_on>2017-01-26 20:14:39</sys_created_on>
            <sys_domain>global</sys_domain>
            <sys_domain_path>/</sys_domain_path>
            <sys_id>28b229350fa03200cd674f8ce1050eac</sys_id>
            <sys_mod_count>0</sys_mod_count>
            <sys_updated_by>admin</sys_updated_by>
            <sys_updated_on>2017-01-26 20:14:39</sys_updated_on>
            <value>15</value>
        </sys_choice>
        <sys_choice action="INSERT_OR_UPDATE">
            <dependent_value/>
            <element>state</element>
            <hint/>
            <inactive>false</inactive>
            <label>Awaiting Feedback</label>
            <language>en</language>
            <name>x_58872_needit_needit</name>
            <sequence>3</sequence>
            <sys_created_by>admin</sys_created_by>
            <sys_created_on>2017-01-26 20:14:39</sys_created_on>
            <sys_domain>global</sys_domain>
            <sys_domain_path>/</sys_domain_path>
            <sys_id>60b229350fa03200cd674f8ce1050eae</sys_id>
            <sys_mod_count>0</sys_mod_count>
            <sys_updated_by>admin</sys_updated_by>
            <sys_updated_on>2017-01-26 20:14:39</sys_updated_on>
            <value>16</value>
        </sys_choice>
        <sys_choice action="INSERT_OR_UPDATE">
            <dependent_value/>
            <element>state</element>
            <hint/>
            <inactive>false</inactive>
            <label>Closed Complete</label>
            <language>en</language>
            <name>x_58872_needit_needit</name>
            <sequence>4</sequence>
            <sys_created_by>admin</sys_created_by>
            <sys_created_on>2017-01-26 20:14:39</sys_created_on>
            <sys_domain>global</sys_domain>
            <sys_domain_path>/</sys_domain_path>
            <sys_id>a8b229350fa03200cd674f8ce1050eaf</sys_id>
            <sys_mod_count>0</sys_mod_count>
            <sys_updated_by>admin</sys_updated_by>
            <sys_updated_on>2017-01-26 20:14:39</sys_updated_on>
            <value>3</value>
        </sys_choice>
        <sys_choice action="INSERT_OR_UPDATE">
            <dependent_value/>
            <element>state</element>
            <hint/>
            <inactive>false</inactive>
            <label>Withdrawn</label>
            <language>en</language>
            <name>x_58872_needit_needit</name>
            <sequence>5</sequence>
            <sys_created_by>admin</sys_created_by>
            <sys_created_on>2017-01-26 20:14:39</sys_created_on>
            <sys_domain>global</sys_domain>
            <sys_domain_path>/</sys_domain_path>
            <sys_id>a0b229350fa03200cd674f8ce1050eb1</sys_id>
            <sys_mod_count>0</sys_mod_count>
            <sys_updated_by>admin</sys_updated_by>
            <sys_updated_on>2017-01-26 20:14:39</sys_updated_on>
            <value>8</value>
        </sys_choice>
        <sys_choice_set action="INSERT_OR_UPDATE">
            <element>state</element>
            <name>x_58872_needit_needit</name>
            <sys_class_name>sys_choice_set</sys_class_name>
            <sys_created_by>admin</sys_created_by>
            <sys_created_on>2017-01-26 20:14:39</sys_created_on>
            <sys_id>433ce6b84f431300874e8020a310c78f</sys_id>
            <sys_mod_count>1</sys_mod_count>
            <sys_name>state</sys_name>
            <sys_package display_value="NeedIt" source="x_58872_needit">6ead8e780f603200cd674f8ce1050ed1</sys_package>
            <sys_policy/>
            <sys_scope display_value="NeedIt">6ead8e780f603200cd674f8ce1050ed1</sys_scope>
            <sys_update_name>sys_choice_x_58872_needit_needit_state</sys_update_name>
            <sys_updated_by>admin</sys_updated_by>
            <sys_updated_on>2017-01-26 20:14:39</sys_updated_on>
        </sys_choice_set>
    </sys_choice>
<sys_update_version action="INSERT_OR_UPDATE">
        <action>DELETE</action>
        <application display_value="NeedIt">6ead8e780f603200cd674f8ce1050ed1</application>
        <file_path/>
        <instance_id>11d472a3dba3bfc449eac59705961911</instance_id>
        <instance_name>dev92712</instance_name>
        <name>sys_choice_x_58872_needit_needit_state</name>
        <payload><![CDATA[<?xml version="1.0" encoding="UTF-8"?><record_update>
    <sys_choice action="INSERT_OR_UPDATE" field="state" table="x_58872_needit_needit" version="3">
        <sys_choice action="INSERT_OR_UPDATE">
            <dependent_value/>
            <element>state</element>
            <hint/>
            <inactive>false</inactive>
            <label>Requested</label>
            <language>en</language>
            <name>x_58872_needit_needit</name>
            <sequence>0</sequence>
            <sys_created_by>admin</sys_created_by>
            <sys_created_on>2017-01-26 20:14:39</sys_created_on>
            <sys_domain>global</sys_domain>
            <sys_domain_path>/</sys_domain_path>
            <sys_id>e0b229350fa03200cd674f8ce1050ea9</sys_id>
            <sys_mod_count>0</sys_mod_count>
            <sys_updated_by>admin</sys_updated_by>
            <sys_updated_on>2017-01-26 20:14:39</sys_updated_on>
            <value>13</value>
        </sys_choice>
        <sys_choice action="INSERT_OR_UPDATE">
            <dependent_value/>
            <element>state</element>
            <hint/>
            <inactive>false</inactive>
            <label>Awaiting Approval</label>
            <language>en</language>
            <name>x_58872_needit_needit</name>
            <sequence>1</sequence>
            <sys_created_by>admin</sys_created_by>
            <sys_created_on>2017-01-26 20:14:39</sys_created_on>
            <sys_domain>global</sys_domain>
            <sys_domain_path>/</sys_domain_path>
            <sys_id>ecb229350fa03200cd674f8ce1050eaa</sys_id>
            <sys_mod_count>0</sys_mod_count>
            <sys_updated_by>admin</sys_updated_by>
            <sys_updated_on>2017-01-26 20:14:39</sys_updated_on>
            <value>14</value>
        </sys_choice>
        <sys_choice action="INSERT_OR_UPDATE">
            <dependent_value/>
            <element>state</element>
            <hint/>
            <inactive>false</inactive>
            <label>Approved</label>
            <language>en</language>
            <name>x_58872_needit_needit</name>
            <sequence>2</sequence>
            <sys_created_by>admin</sys_created_by>
            <sys_created_on>2017-01-26 20:14:39</sys_created_on>
            <sys_domain>global</sys_domain>
            <sys_domain_path>/</sys_domain_path>
            <sys_id>28b229350fa03200cd674f8ce1050eac</sys_id>
            <sys_mod_count>0</sys_mod_count>
            <sys_updated_by>admin</sys_updated_by>
            <sys_updated_on>2017-01-26 20:14:39</sys_updated_on>
            <value>15</value>
        </sys_choice>
        <sys_choice action="INSERT_OR_UPDATE">
            <dependent_value/>
            <element>state</element>
            <hint/>
            <inactive>false</inactive>
            <label>Awaiting Feedback</label>
            <language>en</language>
            <name>x_58872_needit_needit</name>
            <sequence>3</sequence>
            <sys_created_by>admin</sys_created_by>
            <sys_created_on>2017-01-26 20:14:39</sys_created_on>
            <sys_domain>global</sys_domain>
            <sys_domain_path>/</sys_domain_path>
            <sys_id>60b229350fa03200cd674f8ce1050eae</sys_id>
            <sys_mod_count>0</sys_mod_count>
            <sys_updated_by>admin</sys_updated_by>
            <sys_updated_on>2017-01-26 20:14:39</sys_updated_on>
            <value>16</value>
        </sys_choice>
        <sys_choice action="INSERT_OR_UPDATE">
            <dependent_value/>
            <element>state</element>
            <hint/>
            <inactive>false</inactive>
            <label>Closed Complete</label>
            <language>en</language>
            <name>x_58872_needit_needit</name>
            <sequence>4</sequence>
            <sys_created_by>admin</sys_created_by>
            <sys_created_on>2017-01-26 20:14:39</sys_created_on>
            <sys_domain>global</sys_domain>
            <sys_domain_path>/</sys_domain_path>
            <sys_id>a8b229350fa03200cd674f8ce1050eaf</sys_id>
            <sys_mod_count>0</sys_mod_count>
            <sys_updated_by>admin</sys_updated_by>
            <sys_updated_on>2017-01-26 20:14:39</sys_updated_on>
            <value>3</value>
        </sys_choice>
        <sys_choice action="INSERT_OR_UPDATE">
            <dependent_value/>
            <element>state</element>
            <hint/>
            <inactive>false</inactive>
            <label>Withdrawn</label>
            <language>en</language>
            <name>x_58872_needit_needit</name>
            <sequence>5</sequence>
            <sys_created_by>admin</sys_created_by>
            <sys_created_on>2017-01-26 20:14:39</sys_created_on>
            <sys_domain>global</sys_domain>
            <sys_domain_path>/</sys_domain_path>
            <sys_id>a0b229350fa03200cd674f8ce1050eb1</sys_id>
            <sys_mod_count>0</sys_mod_count>
            <sys_updated_by>admin</sys_updated_by>
            <sys_updated_on>2017-01-26 20:14:39</sys_updated_on>
            <value>8</value>
        </sys_choice>
        <sys_choice_set action="INSERT_OR_UPDATE">
            <element>state</element>
            <name>x_58872_needit_needit</name>
            <sys_class_name>sys_choice_set</sys_class_name>
            <sys_created_by>admin</sys_created_by>
            <sys_created_on>2017-01-26 20:14:39</sys_created_on>
            <sys_id>433ce6b84f431300874e8020a310c78f</sys_id>
            <sys_mod_count>1</sys_mod_count>
            <sys_name>state</sys_name>
            <sys_package display_value="NeedIt" source="x_58872_needit">6ead8e780f603200cd674f8ce1050ed1</sys_package>
            <sys_policy/>
            <sys_scope display_value="NeedIt">6ead8e780f603200cd674f8ce1050ed1</sys_scope>
            <sys_update_name>sys_choice_x_58872_needit_needit_state</sys_update_name>
            <sys_updated_by>admin</sys_updated_by>
            <sys_updated_on>2017-01-26 20:14:39</sys_updated_on>
        </sys_choice_set>
    </sys_choice>
</record_update>]]></payload>
        <payload_hash>-1231798200</payload_hash>
        <record_name>NeedIt.State</record_name>
        <reverted_from/>
        <source>3db179c2db371010d6500181ca96192b</source>
        <source_table>sys_upgrade_history</source_table>
        <state>previous</state>
        <sys_created_by>admin</sys_created_by>
        <sys_created_on>2020-10-13 06:29:58</sys_created_on>
        <sys_id>49c13dc2db371010d6500181ca9619f5</sys_id>
        <sys_mod_count>0</sys_mod_count>
        <sys_recorded_at>17520a6b8e50000001</sys_recorded_at>
        <sys_updated_by>admin</sys_updated_by>
        <sys_updated_on>2020-10-13 06:29:58</sys_updated_on>
        <type>Choice list</type>
        <update_guid>c5c13dc21d37101020701683aa2763f5</update_guid>
        <update_guid_history>c5c13dc21d37101020701683aa2763f5:0,4fb1b9c242371010accbe3e28e45981f:1528579032,87b1b9c22e37101072e069d92a62e91c:1886447883,83b1b9c2f0371010fea7746dc28e1819:-1196625253,8fb1b9c2013710109b24c5cd80e64115:-1669741480,4bb1b9c209371010285d4e47bca7ae12:775889921,07b1b9c2da37101092b3379947e2ec0f:-1246223066,852e30b5bf77101043524ec7f02a9322:0,5b1ebc75c0771010989dd3db907aa01d:1528579032,931ebc7549771010d990bc004f00361a:1886447883,9f1ebc75b1771010a8db40bb1ad13d16:-1196625253,9b1ebc7541771010f567c8a6de834013:-1669741480,971ebc7519771010f371d309c3b83c10:775889921,931ebc75c27710100e685acef6d0680d:-1246223066,01b63c315f771010cb05b876ba80d846:0,7ba6b83146771010c70e95ad92378c5a:1528579032,b3a6b831b6771010839f68f9726c9057:1886447883,bfa6b831b877101038b20d9557048b53:-1196625253,bba6b831f97710105503d6d31ff79b50:-1669741480,b7a6b831ee771010aa0f3b3806ee9d4d:775889921,fba6b831c3771010675d97d5f4aa7d3d:-1246223066,8c9920f554371010e479d170782120a8:0,8789acb591371010834ad84c64e817e9:1528579032,cf89acb5ff371010591e9767177db4e5:1886447883,cb89acb5513710106379a090dca8f1e2:-1196625253,c789acb5993710106f13399a55465ddf:-1669741480,c389acb5853710105f037dd92b4f15dc:775889921,cf89acb52b3710107da9515e5f1edcd8:-1246223066,16f26c713e3710108ebdf94463f769f5:0,15f22c71863710100681d930c9611391:1528579032,5df22c7134371010c93d5d73022ee48d:1886447883,59f22c71403710108ab3ec34b3d6ce8a:-1196625253,55f22c713c371010a1c9b16a06899087:-1669741480,11f22c71dd37101010eb54bd69268684:775889921,d9f22c71903710109c0ad2ad4df5b280:-1246223066,66dc5c3d81f3101042104c98a9ea6597:0,a1dcd83d99f3101096dc791848482ce4:1528579032,e9dcd83d32f31010b64e5d69c399d3e0:1886447883,e5dcd83df0f31010500a2f16eb6f9add:-1196625253,e1dcd83da6f31010068bd4afcbf351da:-1669741480,addcd83d61f31010efb449594b7bc4d6:775889921,69dcd83db7f31010420a56d5778149d3:-1246223066,3a79b325adb31010e0a6d06e6cb0e0a8:0,a5793325e5b3101067b906762f7db649:1528579032,ed7933250ab31010114d43477ce7bf45:1886447883,e97933254db3101097007ca68b5a4242:-1196625253,e579332563b31010af99fe2af68d123f:-1669741480,e17933250bb31010273c97b703dd443c:775889921,ed79332501b31010d6f39351680b9e38:-1246223066,cbeae7697c7310105d11db3a036bde38:0,fdea6769e77310106bc13f955583c721:1528579032,39ea676951731010f1bfe08570f1721e:1886447883,35ea676934731010b7b9bf24facd951b:-1196625253,31ea676977731010d86543a172e44018:-1669741480,3dea67699e731010ba4f7e8653105b14:775889921,39ea6769ee73101004f1573d705a4211:-1246223066,19046b259f731010cd738a60d3727aad:0,2c042b25aa7310100d398ee638f7545c:1528579032,64042b25e37310101e308555a7453759:1886447883,60042b25b07310109a2cc4e825804556:-1196625253,6c042b2553731010609babc434d52a52:-1669741480,68042b2564731010ce74acbc0bb7a34f:775889921,24042b25a27310101e92a5cc14400a4c:-1246223066,8025a978d2b35010f4394ba7461e5d48:0,2615a57857b350104a53192f05ba34f7:1528579032,6e15a5782db350109b2aac5667d087f3:1886447883,6e15a57802b35010c42f883af24758be:-1196625253,6a15a578b5b35010846a5a76ff466ebb:-1669741480,6615a57862b350101ba1745b79a219b8:775889921,6215a57895b350105ad7127344eb18b5:-1246223066,90eadd3ceb3f101049fae9ccdf83bfc3:0,6ada1d3c843f101098b3097faf2b4060:1528579032,a2da1d3ca23f1010245de7950c4bd95d:1886447883,e6da1d3cd23f10106f6abd4380ad534d:-1196625253,e2da1d3cd33f1010dc15f1567e95de4a:-1669741480,eeda1d3c7f3f1010b6fb814245c24646:775889921,aada1d3c813f101022126afbf4dbc243:-1246223066,e0319170993b1010196f6d8bcd674a1b:0,9e211d30d63b1010c65283777321a32c:1528579032,d6211d30d23b10103178a2ef5a559629:1886447883,1e211d302b3b101056ec2235494c2119:-1196625253,1a211d30f93b1010c59b722162bc5216:-1669741480,16211d307a3b1010348c1b3dbd947f13:775889921,12211d30153b10105788396c2244b610:-1246223066,ea1e8578e8771010d191d8691b4bedc7:-1617139336</update_guid_history>
    </sys_update_version>
    <sys_metadata_delete action="INSERT_OR_UPDATE">
        <sys_audit_delete/>
        <sys_class_name>sys_metadata_delete</sys_class_name>
        <sys_created_by>admin</sys_created_by>
        <sys_created_on>2020-10-16 01:52:34</sys_created_on>
        <sys_db_object display_value="" name="sys_choice_set">sys_choice_set</sys_db_object>
        <sys_id>d289794adb371010d6500181ca96191f</sys_id>
        <sys_metadata>d289794adb371010d6500181ca96191f</sys_metadata>
        <sys_mod_count>0</sys_mod_count>
        <sys_name>state</sys_name>
        <sys_package display_value="NeedIt" source="x_58872_needit">6ead8e780f603200cd674f8ce1050ed1</sys_package>
        <sys_parent/>
        <sys_policy/>
        <sys_scope display_value="NeedIt">6ead8e780f603200cd674f8ce1050ed1</sys_scope>
        <sys_scope_delete display_value="">94872a8897db403e8ee69a431de2fca4</sys_scope_delete>
        <sys_update_name>sys_choice_x_58872_needit_needit_state</sys_update_name>
        <sys_update_version display_value="sys_choice_x_58872_needit_needit_state">49c13dc2db371010d6500181ca9619f5</sys_update_version>
        <sys_updated_by>admin</sys_updated_by>
        <sys_updated_on>2020-10-16 01:52:34</sys_updated_on>
    </sys_metadata_delete>
</record_update>
